README.rst
setup.py
byoci/__init__.py
byoci/commands.py
byoci/options.py
byoci.egg-info/PKG-INFO
byoci.egg-info/SOURCES.txt
byoci.egg-info/dependency_links.txt
byoci.egg-info/entry_points.txt
byoci.egg-info/requires.txt
byoci.egg-info/top_level.txt
byoci/host/commands.py
byoci/host/config.py
byoci/host/options.py
byoci/monitor/commands.py
byoci/monitor/config.py
byoci/monitor/options.py
byoci/slave/commands.py
byoci/slave/config.py
byoci/slave/containers.py
byoci/slave/gitlab.py
byoci/slave/launchpad.py
byoci/slave/options.py
byoci/slave/ssh.py
byoci/tests/__init__.py
byoci/tests/features.py
byoci/tests/fixtures.py
byoci/tests/test_make_targets.py
byoci/tests/host/assertions.py
byoci/tests/host/features.py
byoci/tests/host/fixtures.py
byoci/tests/host/test_commands.py
byoci/tests/host/test_master.py
byoci/tests/host/test_monitor.py
byoci/tests/host/test_setup.py
byoci/tests/host/test_slave.py
byoci/tests/monitor/features.py
byoci/tests/monitor/fixtures.py
byoci/tests/monitor/test_commands.py
byoci/tests/monitor/test_config.py
byoci/tests/slave/features.py
byoci/tests/slave/fixtures.py
byoci/tests/slave/test_branches.py
byoci/tests/slave/test_commands.py
byoci/tests/slave/test_config.py
byoci/tests/slave/test_containers.py
byoci/tests/slave/test_gitlab.py
byoci/tests/slave/test_launchpad.py
byoci/tests/slave/test_proposals.py
byoci/tests/slave/test_ssh.py
byoci/tests/slave/branches/__init__.py
byoci/tests/slave/branches/bzr.py
byoci/tests/slave/branches/git.py