Metadata-Version: 1.0
Name: byoci
Version: 1.0.4
Summary: Build Your Own Continuous Integration.
Home-page: https://launchpad.net/byoci
Author: Vincent Ladeuil
Author-email: vincent.ladeuil@shiphero.com
License: GPLv3
Platform: UNKNOWN
